multisp/__init__.py
multisp/layer.py
multisp/model.py
multisp/module.py
multisp/preprocess.py
multisp/utils.py
multisp-1.1.1.dist-info/LICENSE.txt
multisp-1.1.1.dist-info/METADATA
multisp-1.1.1.dist-info/WHEEL
multisp-1.1.1.dist-info/top_level.txt
multisp-1.1.1.dist-info/RECORD
