Metadata-Version: 2.1
Name: multisp
Version: 1.1.1
Summary: MultiSP deciphers tissue structure and multicellular communication from spatial multi-omics data
Home-page: https://github.com/ChenfengMo316/MultiSP
Author: Chenfeng Mo
Author-email: mochenfeng316@whu.edu.cn
License: MIT
License-File: LICENSE.txt
Requires-Dist: requests
